{
  "id": "a405db06-90a3-41d0-9109-0b7e96d432c8",
  "prevId": "00000000-0000-0000-0000-000000000000",
  "version": "7",
  "dialect": "postgresql",
  "tables": {
    "public.app_deployments": {
      "name": "app_deployments",
      "schema": "",
      "columns": {
        "app_id": {
          "name": "app_id",
          "type": "uuid",
          "primaryKey": false,
          "notNull": true
        },
        "created_at": {
          "name": "created_at",
          "type": "timestamp",
          "primaryKey": false,
          "notNull": true,
          "default": "now()"
        },
        "deployment_url": {
          "name": "deployment_url",
          "type": "text",
          "primaryKey": true,
          "notNull": true
        },
        "deployment_id": {
          "name": "deployment_id",
          "type": "text",
          "primaryKey": false,
          "notNull": true
        },
        "commit": {
          "name": "commit",
          "type": "text",
          "primaryKey": false,
          "notNull": true
        }
      },
      "indexes": {},
      "foreignKeys": {
        "app_deployments_app_id_apps_id_fk": {
          "name": "app_deployments_app_id_apps_id_fk",
          "tableFrom": "app_deployments",
          "tableTo": "apps",
          "columnsFrom": [
            "app_id"
          ],
          "columnsTo": [
            "id"
          ],
          "onDelete": "cascade",
          "onUpdate": "no action"
        }
      },
      "compositePrimaryKeys": {},
      "uniqueConstraints": {},
      "policies": {},
      "checkConstraints": {},
      "isRLSEnabled": false
    },
    "public.app_domains": {
      "name": "app_domains",
      "schema": "",
      "columns": {
        "id": {
          "name": "id",
          "type": "uuid",
          "primaryKey": true,
          "notNull": true,
          "default": "gen_random_uuid()"
        },
        "app_id": {
          "name": "app_id",
          "type": "uuid",
          "primaryKey": false,
          "notNull": true
        },
        "created_at": {
          "name": "created_at",
          "type": "timestamp",
          "primaryKey": false,
          "notNull": true,
          "default": "now()"
        },
        "domain": {
          "name": "domain",
          "type": "text",
          "primaryKey": false,
          "notNull": true
        }
      },
      "indexes": {},
      "foreignKeys": {
        "app_domains_app_id_apps_id_fk": {
          "name": "app_domains_app_id_apps_id_fk",
          "tableFrom": "app_domains",
          "tableTo": "apps",
          "columnsFrom": [
            "app_id"
          ],
          "columnsTo": [
            "id"
          ],
          "onDelete": "cascade",
          "onUpdate": "no action"
        }
      },
      "compositePrimaryKeys": {},
      "uniqueConstraints": {},
      "policies": {},
      "checkConstraints": {},
      "isRLSEnabled": false
    },
    "public.app_users": {
      "name": "app_users",
      "schema": "",
      "columns": {
        "user_id": {
          "name": "user_id",
          "type": "text",
          "primaryKey": false,
          "notNull": true
        },
        "app_id": {
          "name": "app_id",
          "type": "uuid",
          "primaryKey": false,
          "notNull": true
        },
        "created_at": {
          "name": "created_at",
          "type": "timestamp",
          "primaryKey": false,
          "notNull": true,
          "default": "now()"
        },
        "permissions": {
          "name": "permissions",
          "type": "app_user_permission",
          "typeSchema": "public",
          "primaryKey": false,
          "notNull": false
        },
        "freestyle_identity": {
          "name": "freestyle_identity",
          "type": "text",
          "primaryKey": false,
          "notNull": true
        },
        "freestyle_access_token": {
          "name": "freestyle_access_token",
          "type": "text",
          "primaryKey": false,
          "notNull": true
        },
        "freestyle_access_token_id": {
          "name": "freestyle_access_token_id",
          "type": "text",
          "primaryKey": false,
          "notNull": true
        }
      },
      "indexes": {},
      "foreignKeys": {
        "app_users_app_id_apps_id_fk": {
          "name": "app_users_app_id_apps_id_fk",
          "tableFrom": "app_users",
          "tableTo": "apps",
          "columnsFrom": [
            "app_id"
          ],
          "columnsTo": [
            "id"
          ],
          "onDelete": "cascade",
          "onUpdate": "no action"
        }
      },
      "compositePrimaryKeys": {},
      "uniqueConstraints": {},
      "policies": {},
      "checkConstraints": {},
      "isRLSEnabled": false
    },
    "public.apps": {
      "name": "apps",
      "schema": "",
      "columns": {
        "id": {
          "name": "id",
          "type": "uuid",
          "primaryKey": true,
          "notNull": true,
          "default": "gen_random_uuid()"
        },
        "name": {
          "name": "name",
          "type": "text",
          "primaryKey": false,
          "notNull": true,
          "default": "'Unnamed App'"
        },
        "description": {
          "name": "description",
          "type": "text",
          "primaryKey": false,
          "notNull": true,
          "default": "'No description'"
        },
        "git_repo": {
          "name": "git_repo",
          "type": "text",
          "primaryKey": false,
          "notNull": true
        },
        "created_at": {
          "name": "created_at",
          "type": "timestamp",
          "primaryKey": false,
          "notNull": true,
          "default": "now()"
        },
        "base_id": {
          "name": "base_id",
          "type": "text",
          "primaryKey": false,
          "notNull": true,
          "default": "'nextjs-dkjfgdf'"
        }
      },
      "indexes": {},
      "foreignKeys": {},
      "compositePrimaryKeys": {},
      "uniqueConstraints": {},
      "policies": {},
      "checkConstraints": {},
      "isRLSEnabled": false
    },
    "public.messages": {
      "name": "messages",
      "schema": "",
      "columns": {
        "id": {
          "name": "id",
          "type": "text",
          "primaryKey": true,
          "notNull": true
        },
        "created_at": {
          "name": "created_at",
          "type": "timestamp",
          "primaryKey": false,
          "notNull": true,
          "default": "now()"
        },
        "app_id": {
          "name": "app_id",
          "type": "uuid",
          "primaryKey": false,
          "notNull": true
        },
        "message": {
          "name": "message",
          "type": "json",
          "primaryKey": false,
          "notNull": true
        }
      },
      "indexes": {},
      "foreignKeys": {
        "messages_app_id_apps_id_fk": {
          "name": "messages_app_id_apps_id_fk",
          "tableFrom": "messages",
          "tableTo": "apps",
          "columnsFrom": [
            "app_id"
          ],
          "columnsTo": [
            "id"
          ],
          "onDelete": "cascade",
          "onUpdate": "no action"
        }
      },
      "compositePrimaryKeys": {},
      "uniqueConstraints": {},
      "policies": {},
      "checkConstraints": {},
      "isRLSEnabled": false
    }
  },
  "enums": {
    "public.app_user_permission": {
      "name": "app_user_permission",
      "schema": "public",
      "values": [
        "read",
        "write",
        "admin"
      ]
    }
  },
  "schemas": {},
  "sequences": {},
  "roles": {},
  "policies": {},
  "views": {},
  "_meta": {
    "columns": {},
    "schemas": {},
    "tables": {}
  }
}